rtl/mul.sv
`timescale 1ps/1ps

module mul (
    input logic [31:0] A,
    input logic [31:0] B,
    output logic [31:0] C
);

assign C = A * B;
    
endmodule

tests/mul_tb/mul_tb.sv
module mul_tb;

logic [31:0] A;
logic [31:0] B;
logic [31:0] C;

mul mul(
    .A(A),
    .B(B),
    .C(C)
);

initial begin
    if ($test$plusargs("dump") || 1) begin
        $dumpfile("wave.vcd");
        $dumpvars(0, mul_tb);
    end
end

function automatic [31:0] mul_ref(input [31:0] A, input [31:0] B);
    return A * B;
endfunction

task automatic send_and_check(input logic [31:0] A_test, input logic [31:0] B_test);
    logic [31:0] expected;

    A = A_test;
    B = B_test;

    #1;

    expected = mul_ref(A, B);
endtask //automatic

initial begin

    A = '0;
    B = '0;
    #1;

    for(int i = 1; i <= 10; i++) begin
        for (int j = 1; j <= 10; j++) begin
            send_and_check(i, j);
        end
    end

    $display("Test Complete");
    $finish;

end


endmodule

tests/mul_tb/mul_wave.vcd
$version Generated by VerilatedVcd $end
$timescale 1ps $end
 $scope module $rootio $end
 $upscope $end
 $scope module mul_tb $end
  $var wire 32 # A [31:0] $end
  $var wire 32 $ B [31:0] $end
  $var wire 32 % C [31:0] $end
  $scope module dut $end
   $var wire 32 # A [31:0] $end
   $var wire 32 $ B [31:0] $end
   $var wire 32 % C [31:0] $end
  $upscope $end
 $upscope $end
$enddefinitions $end


#0
b00000000000000000000000000000000 #
b00000000000000000000000000000000 $
b00000000000000000000000000000000 %
#1000
#2000
b00000000000000000000000000000001 #
b00000000000000000000000000000001 $
b00000000000000000000000000000001 %
#3000
b00000000000000000000000000000010 #
b00000000000000000000000000000011 $
b00000000000000000000000000000110 %
#4000
b11111111111111111111111111111111 #
b00000000000000000000000000000010 $
b11111111111111111111111111111110 %
#5000
b10000000000000000000000000000000 #
b00000000000000000000000000000000 %
#6000
b00001011000111100101110110011100 #
b01111001011101100111001111000100 $
b00001001001101001011111101110000 %
#7000
b01001000110000101110000011100100 #
b10011110111111011101010100000010 $
b10101111111101110111010111001000 %
#8000
b10111011110101011000111010111100 #
b10010010000101111000001101111000 $
b01011111000010010001110000100000 %
#9000
b00101010000101001111111111100100 #
b11001010101001001001111010110110 $
b10110110111011001010010000011000 %
#10000
b11111100110001000111000101010011 #
b01111101011011111111001110110111 $
b11010001111110111100101101010101 %
#11000
b10001010100110100111110111100001 #
b01101111100111100001011100100001 $
b11111111000101110111000100000001 %
#12000
b00010010010100111111001110000010 #
b11011111100011001010111111000101 $
b11100111001010000100000100001010 %
#13000
b01110011010110000001011000110101 #
b10100100010100011111111101100010 $
b11100000100111000100101101001010 %
#14000
b01100010111110011010101101010110 #
b10101101111110111100100100010010 $
b00011000011001101001001000001100 %
#15000
b11011100011010110100000111110100 #
b10110100001100100011101111111101 $
b11111111110110110110101000100100 %
