rtl/mul.sv
`timescale 1ps/1ps

module mul (
    input logic [31:0] A,
    input logic [31:0] B,
    output logic [31:0] C
);

assign C = A * B;
    
endmodule

tests/mul_tb/mul_tb.sv
module mul_tb;

logic [31:0] A;
logic [31:0] B;
logic [31:0] C;

mul mul(
    .A(A),
    .B(B),
    .C(C)
);

initial begin
    if ($test$plusargs("dump") || 1) begin
        $dumpfile("wave.vcd");
        $dumpvars(0, mul_tb);
    end
end

function automatic [31:0] mul_ref(input [31:0] A, input [31:0] B);
    return A * B;
endfunction

task automatic send_and_check(input logic [31:0] A_test, input logic [31:0] B_test);
    logic [31:0] expected;

    A = A_test;
    B = B_test;

    #1;

    expected = mul_ref(A, B);
endtask //automatic

initial begin

    A = '0;
    B = '0;
    #1;

    for(int i = 1; i <= 10; i++) begin
        for (int j = 1; j <= 10; j++) begin
            send_and_check(i, j);
        end
    end

    $display("Test Complete");
    $finish;

end


endmodule

tests/mul_tb/wave.vcd
$version Generated by VerilatedVcd $end
$timescale 1ps $end
 $scope module $rootio $end
 $upscope $end
 $scope module mul_tb $end
  $var wire 32 # A [31:0] $end
  $var wire 32 $ B [31:0] $end
  $var wire 32 % C [31:0] $end
  $scope module mul $end
   $var wire 32 # A [31:0] $end
   $var wire 32 $ B [31:0] $end
   $var wire 32 % C [31:0] $end
  $upscope $end
  $scope module unnamedblk1 $end
   $var wire 32 & i [31:0] $end
   $scope module unnamedblk2 $end
    $var wire 32 ' j [31:0] $end
   $upscope $end
  $upscope $end
 $upscope $end
$enddefinitions $end


#0
b00000000000000000000000000000000 #
b00000000000000000000000000000000 $
b00000000000000000000000000000000 %
b00000000000000000000000000000000 &
b00000000000000000000000000000000 '
#1000
b00000000000000000000000000000001 #
b00000000000000000000000000000001 $
b00000000000000000000000000000001 %
#2000
b00000000000000000000000000000010 $
b00000000000000000000000000000010 %
b00000000000000000000000000000010 '
#3000
b00000000000000000000000000000011 $
b00000000000000000000000000000011 %
b00000000000000000000000000000011 '
#4000
b00000000000000000000000000000100 $
b00000000000000000000000000000100 %
b00000000000000000000000000000100 '
#5000
b00000000000000000000000000000101 $
b00000000000000000000000000000101 %
b00000000000000000000000000000101 '
#6000
b00000000000000000000000000000110 $
b00000000000000000000000000000110 %
b00000000000000000000000000000110 '
#7000
b00000000000000000000000000000111 $
b00000000000000000000000000000111 %
b00000000000000000000000000000111 '
#8000
b00000000000000000000000000001000 $
b00000000000000000000000000001000 %
b00000000000000000000000000001000 '
#9000
b00000000000000000000000000001001 $
b00000000000000000000000000001001 %
b00000000000000000000000000001001 '
#10000
b00000000000000000000000000001010 $
b00000000000000000000000000001010 %
b00000000000000000000000000001010 '
#11000
b00000000000000000000000000000010 #
b00000000000000000000000000000001 $
b00000000000000000000000000000010 %
b00000000000000000000000000000010 &
b00000000000000000000000000001011 '
#12000
b00000000000000000000000000000010 $
b00000000000000000000000000000100 %
b00000000000000000000000000000010 '
#13000
b00000000000000000000000000000011 $
b00000000000000000000000000000110 %
b00000000000000000000000000000011 '
#14000
b00000000000000000000000000000100 $
b00000000000000000000000000001000 %
b00000000000000000000000000000100 '
#15000
b00000000000000000000000000000101 $
b00000000000000000000000000001010 %
b00000000000000000000000000000101 '
#16000
b00000000000000000000000000000110 $
b00000000000000000000000000001100 %
b00000000000000000000000000000110 '
#17000
b00000000000000000000000000000111 $
b00000000000000000000000000001110 %
b00000000000000000000000000000111 '
#18000
b00000000000000000000000000001000 $
b00000000000000000000000000010000 %
b00000000000000000000000000001000 '
#19000
b00000000000000000000000000001001 $
b00000000000000000000000000010010 %
b00000000000000000000000000001001 '
#20000
b00000000000000000000000000001010 $
b00000000000000000000000000010100 %
b00000000000000000000000000001010 '
#21000
b00000000000000000000000000000011 #
b00000000000000000000000000000001 $
b00000000000000000000000000000011 %
b00000000000000000000000000000011 &
b00000000000000000000000000001011 '
#22000
b00000000000000000000000000000010 $
b00000000000000000000000000000110 %
b00000000000000000000000000000010 '
#23000
b00000000000000000000000000000011 $
b00000000000000000000000000001001 %
b00000000000000000000000000000011 '
#24000
b00000000000000000000000000000100 $
b00000000000000000000000000001100 %
b00000000000000000000000000000100 '
#25000
b00000000000000000000000000000101 $
b00000000000000000000000000001111 %
b00000000000000000000000000000101 '
#26000
b00000000000000000000000000000110 $
b00000000000000000000000000010010 %
b00000000000000000000000000000110 '
#27000
b00000000000000000000000000000111 $
b00000000000000000000000000010101 %
b00000000000000000000000000000111 '
#28000
b00000000000000000000000000001000 $
b00000000000000000000000000011000 %
b00000000000000000000000000001000 '
#29000
b00000000000000000000000000001001 $
b00000000000000000000000000011011 %
b00000000000000000000000000001001 '
#30000
b00000000000000000000000000001010 $
b00000000000000000000000000011110 %
b00000000000000000000000000001010 '
#31000
b00000000000000000000000000000100 #
b00000000000000000000000000000001 $
b00000000000000000000000000000100 %
b00000000000000000000000000000100 &
b00000000000000000000000000001011 '
#32000
b00000000000000000000000000000010 $
b00000000000000000000000000001000 %
b00000000000000000000000000000010 '
#33000
b00000000000000000000000000000011 $
b00000000000000000000000000001100 %
b00000000000000000000000000000011 '
#34000
b00000000000000000000000000000100 $
b00000000000000000000000000010000 %
b00000000000000000000000000000100 '
#35000
b00000000000000000000000000000101 $
b00000000000000000000000000010100 %
b00000000000000000000000000000101 '
#36000
b00000000000000000000000000000110 $
b00000000000000000000000000011000 %
b00000000000000000000000000000110 '
#37000
b00000000000000000000000000000111 $
b00000000000000000000000000011100 %
b00000000000000000000000000000111 '
#38000
b00000000000000000000000000001000 $
b00000000000000000000000000100000 %
b00000000000000000000000000001000 '
#39000
b00000000000000000000000000001001 $
b00000000000000000000000000100100 %
b00000000000000000000000000001001 '
#40000
b00000000000000000000000000001010 $
b00000000000000000000000000101000 %
b00000000000000000000000000001010 '
#41000
b00000000000000000000000000000101 #
b00000000000000000000000000000001 $
b00000000000000000000000000000101 %
b00000000000000000000000000000101 &
b00000000000000000000000000001011 '
#42000
b00000000000000000000000000000010 $
b00000000000000000000000000001010 %
b00000000000000000000000000000010 '
#43000
b00000000000000000000000000000011 $
b00000000000000000000000000001111 %
b00000000000000000000000000000011 '
#44000
b00000000000000000000000000000100 $
b00000000000000000000000000010100 %
b00000000000000000000000000000100 '
#45000
b00000000000000000000000000000101 $
b00000000000000000000000000011001 %
b00000000000000000000000000000101 '
#46000
b00000000000000000000000000000110 $
b00000000000000000000000000011110 %
b00000000000000000000000000000110 '
#47000
b00000000000000000000000000000111 $
b00000000000000000000000000100011 %
b00000000000000000000000000000111 '
#48000
b00000000000000000000000000001000 $
b00000000000000000000000000101000 %
b00000000000000000000000000001000 '
#49000
b00000000000000000000000000001001 $
b00000000000000000000000000101101 %
b00000000000000000000000000001001 '
#50000
b00000000000000000000000000001010 $
b00000000000000000000000000110010 %
b00000000000000000000000000001010 '
#51000
b00000000000000000000000000000110 #
b00000000000000000000000000000001 $
b00000000000000000000000000000110 %
b00000000000000000000000000000110 &
b00000000000000000000000000001011 '
#52000
b00000000000000000000000000000010 $
b00000000000000000000000000001100 %
b00000000000000000000000000000010 '
#53000
b00000000000000000000000000000011 $
b00000000000000000000000000010010 %
b00000000000000000000000000000011 '
#54000
b00000000000000000000000000000100 $
b00000000000000000000000000011000 %
b00000000000000000000000000000100 '
#55000
b00000000000000000000000000000101 $
b00000000000000000000000000011110 %
b00000000000000000000000000000101 '
#56000
b00000000000000000000000000000110 $
b00000000000000000000000000100100 %
b00000000000000000000000000000110 '
#57000
b00000000000000000000000000000111 $
b00000000000000000000000000101010 %
b00000000000000000000000000000111 '
#58000
b00000000000000000000000000001000 $
b00000000000000000000000000110000 %
b00000000000000000000000000001000 '
#59000
b00000000000000000000000000001001 $
b00000000000000000000000000110110 %
b00000000000000000000000000001001 '
#60000
b00000000000000000000000000001010 $
b00000000000000000000000000111100 %
b00000000000000000000000000001010 '
#61000
b00000000000000000000000000000111 #
b00000000000000000000000000000001 $
b00000000000000000000000000000111 %
b00000000000000000000000000000111 &
b00000000000000000000000000001011 '
#62000
b00000000000000000000000000000010 $
b00000000000000000000000000001110 %
b00000000000000000000000000000010 '
#63000
b00000000000000000000000000000011 $
b00000000000000000000000000010101 %
b00000000000000000000000000000011 '
#64000
b00000000000000000000000000000100 $
b00000000000000000000000000011100 %
b00000000000000000000000000000100 '
#65000
b00000000000000000000000000000101 $
b00000000000000000000000000100011 %
b00000000000000000000000000000101 '
#66000
b00000000000000000000000000000110 $
b00000000000000000000000000101010 %
b00000000000000000000000000000110 '
#67000
b00000000000000000000000000000111 $
b00000000000000000000000000110001 %
b00000000000000000000000000000111 '
#68000
b00000000000000000000000000001000 $
b00000000000000000000000000111000 %
b00000000000000000000000000001000 '
#69000
b00000000000000000000000000001001 $
b00000000000000000000000000111111 %
b00000000000000000000000000001001 '
#70000
b00000000000000000000000000001010 $
b00000000000000000000000001000110 %
b00000000000000000000000000001010 '
#71000
b00000000000000000000000000001000 #
b00000000000000000000000000000001 $
b00000000000000000000000000001000 %
b00000000000000000000000000001000 &
b00000000000000000000000000001011 '
#72000
b00000000000000000000000000000010 $
b00000000000000000000000000010000 %
b00000000000000000000000000000010 '
#73000
b00000000000000000000000000000011 $
b00000000000000000000000000011000 %
b00000000000000000000000000000011 '
#74000
b00000000000000000000000000000100 $
b00000000000000000000000000100000 %
b00000000000000000000000000000100 '
#75000
b00000000000000000000000000000101 $
b00000000000000000000000000101000 %
b00000000000000000000000000000101 '
#76000
b00000000000000000000000000000110 $
b00000000000000000000000000110000 %
b00000000000000000000000000000110 '
#77000
b00000000000000000000000000000111 $
b00000000000000000000000000111000 %
b00000000000000000000000000000111 '
#78000
b00000000000000000000000000001000 $
b00000000000000000000000001000000 %
b00000000000000000000000000001000 '
#79000
b00000000000000000000000000001001 $
b00000000000000000000000001001000 %
b00000000000000000000000000001001 '
#80000
b00000000000000000000000000001010 $
b00000000000000000000000001010000 %
b00000000000000000000000000001010 '
#81000
b00000000000000000000000000001001 #
b00000000000000000000000000000001 $
b00000000000000000000000000001001 %
b00000000000000000000000000001001 &
b00000000000000000000000000001011 '
#82000
b00000000000000000000000000000010 $
b00000000000000000000000000010010 %
b00000000000000000000000000000010 '
#83000
b00000000000000000000000000000011 $
b00000000000000000000000000011011 %
b00000000000000000000000000000011 '
#84000
b00000000000000000000000000000100 $
b00000000000000000000000000100100 %
b00000000000000000000000000000100 '
#85000
b00000000000000000000000000000101 $
b00000000000000000000000000101101 %
b00000000000000000000000000000101 '
#86000
b00000000000000000000000000000110 $
b00000000000000000000000000110110 %
b00000000000000000000000000000110 '
#87000
b00000000000000000000000000000111 $
b00000000000000000000000000111111 %
b00000000000000000000000000000111 '
#88000
b00000000000000000000000000001000 $
b00000000000000000000000001001000 %
b00000000000000000000000000001000 '
#89000
b00000000000000000000000000001001 $
b00000000000000000000000001010001 %
b00000000000000000000000000001001 '
#90000
b00000000000000000000000000001010 $
b00000000000000000000000001011010 %
b00000000000000000000000000001010 '
#91000
b00000000000000000000000000001010 #
b00000000000000000000000000000001 $
b00000000000000000000000000001010 %
b00000000000000000000000000001010 &
b00000000000000000000000000001011 '
#92000
b00000000000000000000000000000010 $
b00000000000000000000000000010100 %
b00000000000000000000000000000010 '
#93000
b00000000000000000000000000000011 $
b00000000000000000000000000011110 %
b00000000000000000000000000000011 '
#94000
b00000000000000000000000000000100 $
b00000000000000000000000000101000 %
b00000000000000000000000000000100 '
#95000
b00000000000000000000000000000101 $
b00000000000000000000000000110010 %
b00000000000000000000000000000101 '
#96000
b00000000000000000000000000000110 $
b00000000000000000000000000111100 %
b00000000000000000000000000000110 '
#97000
b00000000000000000000000000000111 $
b00000000000000000000000001000110 %
b00000000000000000000000000000111 '
#98000
b00000000000000000000000000001000 $
b00000000000000000000000001010000 %
b00000000000000000000000000001000 '
#99000
b00000000000000000000000000001001 $
b00000000000000000000000001011010 %
b00000000000000000000000000001001 '
#100000
b00000000000000000000000000001010 $
b00000000000000000000000001100100 %
b00000000000000000000000000001010 '
#101000
b00000000000000000000000000001011 &
b00000000000000000000000000001011 '
