rtl/mul.sv
`timescale 1ps/1ps

module mul (
    input logic CLK,
    input logic [31:0] A,
    input logic [31:0] B,
    output logic [31:0] C
);

logic [31:0] a_q, b_q, c_q;

always_ff @( posedge CLK ) begin
    a_q <= A;
    b_q <= B;
    C <= c_q;
end

assign c_q = a_q * b_q;
    
endmodule

tests/mul_tb/mul_tb.sv
module mul_tb;

logic CLK;
logic [31:0] A;
logic [31:0] B;
logic [31:0] C;

mul mul(
    .CLK(CLK),
    .A(A),
    .B(B),
    .C(C)
);

initial CLK = 0;
always #5 CLK = ~CLK;

initial begin
    if ($test$plusargs("dump") || 1) begin
        $dumpfile("wave.vcd");
        $dumpvars(0, mul_tb);
    end
end

function automatic [31:0] mul_ref(input [31:0] A, input [31:0] B);
    return A * B;
endfunction

task automatic send_and_check(input logic [31:0] A_test, input logic [31:0] B_test);
    logic [31:0] expected = 32'(A_test) * 32'(B_test);

    @(negedge CLK);

    A = A_test;
    B = B_test;

    @(posedge CLK); // capture inputs
    @(posedge CLK); // product registered  to C
    @(negedge CLK);

    if(C != expected)
        $error("[%0t] Mismatch: A=%0d B=%0d C=%0d exp=%0d", $time, A_test, B_test, C, expected);

endtask

initial begin

    A = '0;
    B = '0;
    #1;

    for(int i = 1; i <= 10; i++) begin
        for (int j = 1; j <= 10; j++) begin
            send_and_check(i, j);
        end
    end

    $display("Test Complete");
    $finish;

end


endmodule

tests/mul_tb/wave.vcd
$date
	Sun Sep 21 06:26:57 2025
$end
$version
	Icarus Verilog
$end
$timescale
	1ps
$end
$scope module mul_tb $end
$var wire 32 ! C [31:0] $end
$var reg 32 " A [31:0] $end
$var reg 32 # B [31:0] $end
$var reg 1 $ CLK $end
$scope function mul_ref $end
$upscope $end
$scope module mul $end
$var wire 32 % A [31:0] $end
$var wire 32 & B [31:0] $end
$var wire 1 $ CLK $end
$var wire 32 ' c_q [31:0] $end
$var reg 32 ( C [31:0] $end
$var reg 32 ) a_q [31:0] $end
$var reg 32 * b_q [31:0] $end
$upscope $end
$scope begin $ivl_for_loop0 $end
$var integer 32 + i [31:0] $end
$scope begin $ivl_for_loop1 $end
$var integer 32 , j [31:0] $end
$upscope $end
$upscope $end
$scope task send_and_check $end
$upscope $end
$upscope $end
$enddefinitions $end
$comment Show the parameter values. $end
$dumpall
$end
#0
$dumpvars
b0 ,
b0 +
bx *
bx )
bx (
bx '
b0 &
b0 %
0$
b0 #
b0 "
bx !
$end
#1
b1 ,
b1 +
#5
b0 '
b0 *
b0 )
1$
#10
b1 #
b1 &
b1 "
b1 %
0$
#15
b0 !
b0 (
b1 '
b1 *
b1 )
1$
#20
0$
#25
b1 !
b1 (
1$
#30
b10 ,
0$
#35
1$
#40
b10 #
b10 &
0$
#45
b10 '
b10 *
1$
#50
0$
#55
b10 !
b10 (
1$
#60
b11 ,
0$
#65
1$
#70
b11 #
b11 &
0$
#75
b11 '
b11 *
1$
#80
0$
#85
b11 !
b11 (
1$
#90
b100 ,
0$
#95
1$
#100
b100 #
b100 &
0$
#105
b100 '
b100 *
1$
#110
0$
#115
b100 !
b100 (
1$
#120
b101 ,
0$
#125
1$
#130
b101 #
b101 &
0$
#135
b101 '
b101 *
1$
#140
0$
#145
b101 !
b101 (
1$
#150
b110 ,
0$
#155
1$
#160
b110 #
b110 &
0$
#165
b110 '
b110 *
1$
#170
0$
#175
b110 !
b110 (
1$
#180
b111 ,
0$
#185
1$
#190
b111 #
b111 &
0$
#195
b111 '
b111 *
1$
#200
0$
#205
b111 !
b111 (
1$
#210
b1000 ,
0$
#215
1$
#220
b1000 #
b1000 &
0$
#225
b1000 '
b1000 *
1$
#230
0$
#235
b1000 !
b1000 (
1$
#240
b1001 ,
0$
#245
1$
#250
b1001 #
b1001 &
0$
#255
b1001 '
b1001 *
1$
#260
0$
#265
b1001 !
b1001 (
1$
#270
b1010 ,
0$
#275
1$
#280
b1010 #
b1010 &
0$
#285
b1010 '
b1010 *
1$
#290
0$
#295
b1010 !
b1010 (
1$
#300
b10 +
b1 ,
0$
#305
1$
#310
b1 #
b1 &
b10 "
b10 %
0$
#315
b1 *
b10 '
b10 )
1$
#320
0$
#325
b10 !
b10 (
1$
#330
b10 ,
0$
#335
1$
#340
b10 #
b10 &
0$
#345
b100 '
b10 *
1$
#350
0$
#355
b100 !
b100 (
1$
#360
b11 ,
0$
#365
1$
#370
b11 #
b11 &
0$
#375
b110 '
b11 *
1$
#380
0$
#385
b110 !
b110 (
1$
#390
b100 ,
0$
#395
1$
#400
b100 #
b100 &
0$
#405
b1000 '
b100 *
1$
#410
0$
#415
b1000 !
b1000 (
1$
#420
b101 ,
0$
#425
1$
#430
b101 #
b101 &
0$
#435
b1010 '
b101 *
1$
#440
0$
#445
b1010 !
b1010 (
1$
#450
b110 ,
0$
#455
1$
#460
b110 #
b110 &
0$
#465
b1100 '
b110 *
1$
#470
0$
#475
b1100 !
b1100 (
1$
#480
b111 ,
0$
#485
1$
#490
b111 #
b111 &
0$
#495
b1110 '
b111 *
1$
#500
0$
#505
b1110 !
b1110 (
1$
#510
b1000 ,
0$
#515
1$
#520
b1000 #
b1000 &
0$
#525
b10000 '
b1000 *
1$
#530
0$
#535
b10000 !
b10000 (
1$
#540
b1001 ,
0$
#545
1$
#550
b1001 #
b1001 &
0$
#555
b10010 '
b1001 *
1$
#560
0$
#565
b10010 !
b10010 (
1$
#570
b1010 ,
0$
#575
1$
#580
b1010 #
b1010 &
0$
#585
b10100 '
b1010 *
1$
#590
0$
#595
b10100 !
b10100 (
1$
#600
b11 +
b1 ,
0$
#605
1$
#610
b1 #
b1 &
b11 "
b11 %
0$
#615
b1 *
b11 '
b11 )
1$
#620
0$
#625
b11 !
b11 (
1$
#630
b10 ,
0$
#635
1$
#640
b10 #
b10 &
0$
#645
b110 '
b10 *
1$
#650
0$
#655
b110 !
b110 (
1$
#660
b11 ,
0$
#665
1$
#670
b11 #
b11 &
0$
#675
b1001 '
b11 *
1$
#680
0$
#685
b1001 !
b1001 (
1$
#690
b100 ,
0$
#695
1$
#700
b100 #
b100 &
0$
#705
b1100 '
b100 *
1$
#710
0$
#715
b1100 !
b1100 (
1$
#720
b101 ,
0$
#725
1$
#730
b101 #
b101 &
0$
#735
b1111 '
b101 *
1$
#740
0$
#745
b1111 !
b1111 (
1$
#750
b110 ,
0$
#755
1$
#760
b110 #
b110 &
0$
#765
b10010 '
b110 *
1$
#770
0$
#775
b10010 !
b10010 (
1$
#780
b111 ,
0$
#785
1$
#790
b111 #
b111 &
0$
#795
b10101 '
b111 *
1$
#800
0$
#805
b10101 !
b10101 (
1$
#810
b1000 ,
0$
#815
1$
#820
b1000 #
b1000 &
0$
#825
b11000 '
b1000 *
1$
#830
0$
#835
b11000 !
b11000 (
1$
#840
b1001 ,
0$
#845
1$
#850
b1001 #
b1001 &
0$
#855
b11011 '
b1001 *
1$
#860
0$
#865
b11011 !
b11011 (
1$
#870
b1010 ,
0$
#875
1$
#880
b1010 #
b1010 &
0$
#885
b11110 '
b1010 *
1$
#890
0$
#895
b11110 !
b11110 (
1$
#900
b100 +
b1 ,
0$
#905
1$
#910
b1 #
b1 &
b100 "
b100 %
0$
#915
b1 *
b100 '
b100 )
1$
#920
0$
#925
b100 !
b100 (
1$
#930
b10 ,
0$
#935
1$
#940
b10 #
b10 &
0$
#945
b1000 '
b10 *
1$
#950
0$
#955
b1000 !
b1000 (
1$
#960
b11 ,
0$
#965
1$
#970
b11 #
b11 &
0$
#975
b1100 '
b11 *
1$
#980
0$
#985
b1100 !
b1100 (
1$
#990
b100 ,
0$
#995
1$
#1000
b100 #
b100 &
0$
#1005
b10000 '
b100 *
1$
#1010
0$
#1015
b10000 !
b10000 (
1$
#1020
b101 ,
0$
#1025
1$
#1030
b101 #
b101 &
0$
#1035
b10100 '
b101 *
1$
#1040
0$
#1045
b10100 !
b10100 (
1$
#1050
b110 ,
0$
#1055
1$
#1060
b110 #
b110 &
0$
#1065
b11000 '
b110 *
1$
#1070
0$
#1075
b11000 !
b11000 (
1$
#1080
b111 ,
0$
#1085
1$
#1090
b111 #
b111 &
0$
#1095
b11100 '
b111 *
1$
#1100
0$
#1105
b11100 !
b11100 (
1$
#1110
b1000 ,
0$
#1115
1$
#1120
b1000 #
b1000 &
0$
#1125
b100000 '
b1000 *
1$
#1130
0$
#1135
b100000 !
b100000 (
1$
#1140
b1001 ,
0$
#1145
1$
#1150
b1001 #
b1001 &
0$
#1155
b100100 '
b1001 *
1$
#1160
0$
#1165
b100100 !
b100100 (
1$
#1170
b1010 ,
0$
#1175
1$
#1180
b1010 #
b1010 &
0$
#1185
b101000 '
b1010 *
1$
#1190
0$
#1195
b101000 !
b101000 (
1$
#1200
b101 +
b1 ,
0$
#1205
1$
#1210
b1 #
b1 &
b101 "
b101 %
0$
#1215
b1 *
b101 '
b101 )
1$
#1220
0$
#1225
b101 !
b101 (
1$
#1230
b10 ,
0$
#1235
1$
#1240
b10 #
b10 &
0$
#1245
b1010 '
b10 *
1$
#1250
0$
#1255
b1010 !
b1010 (
1$
#1260
b11 ,
0$
#1265
1$
#1270
b11 #
b11 &
0$
#1275
b1111 '
b11 *
1$
#1280
0$
#1285
b1111 !
b1111 (
1$
#1290
b100 ,
0$
#1295
1$
#1300
b100 #
b100 &
0$
#1305
b10100 '
b100 *
1$
#1310
0$
#1315
b10100 !
b10100 (
1$
#1320
b101 ,
0$
#1325
1$
#1330
b101 #
b101 &
0$
#1335
b11001 '
b101 *
1$
#1340
0$
#1345
b11001 !
b11001 (
1$
#1350
b110 ,
0$
#1355
1$
#1360
b110 #
b110 &
0$
#1365
b11110 '
b110 *
1$
#1370
0$
#1375
b11110 !
b11110 (
1$
#1380
b111 ,
0$
#1385
1$
#1390
b111 #
b111 &
0$
#1395
b100011 '
b111 *
1$
#1400
0$
#1405
b100011 !
b100011 (
1$
#1410
b1000 ,
0$
#1415
1$
#1420
b1000 #
b1000 &
0$
#1425
b101000 '
b1000 *
1$
#1430
0$
#1435
b101000 !
b101000 (
1$
#1440
b1001 ,
0$
#1445
1$
#1450
b1001 #
b1001 &
0$
#1455
b101101 '
b1001 *
1$
#1460
0$
#1465
b101101 !
b101101 (
1$
#1470
b1010 ,
0$
#1475
1$
#1480
b1010 #
b1010 &
0$
#1485
b110010 '
b1010 *
1$
#1490
0$
#1495
b110010 !
b110010 (
1$
#1500
b110 +
b1 ,
0$
#1505
1$
#1510
b1 #
b1 &
b110 "
b110 %
0$
#1515
b1 *
b110 '
b110 )
1$
#1520
0$
#1525
b110 !
b110 (
1$
#1530
b10 ,
0$
#1535
1$
#1540
b10 #
b10 &
0$
#1545
b1100 '
b10 *
1$
#1550
0$
#1555
b1100 !
b1100 (
1$
#1560
b11 ,
0$
#1565
1$
#1570
b11 #
b11 &
0$
#1575
b10010 '
b11 *
1$
#1580
0$
#1585
b10010 !
b10010 (
1$
#1590
b100 ,
0$
#1595
1$
#1600
b100 #
b100 &
0$
#1605
b11000 '
b100 *
1$
#1610
0$
#1615
b11000 !
b11000 (
1$
#1620
b101 ,
0$
#1625
1$
#1630
b101 #
b101 &
0$
#1635
b11110 '
b101 *
1$
#1640
0$
#1645
b11110 !
b11110 (
1$
#1650
b110 ,
0$
#1655
1$
#1660
b110 #
b110 &
0$
#1665
b100100 '
b110 *
1$
#1670
0$
#1675
b100100 !
b100100 (
1$
#1680
b111 ,
0$
#1685
1$
#1690
b111 #
b111 &
0$
#1695
b101010 '
b111 *
1$
#1700
0$
#1705
b101010 !
b101010 (
1$
#1710
b1000 ,
0$
#1715
1$
#1720
b1000 #
b1000 &
0$
#1725
b110000 '
b1000 *
1$
#1730
0$
#1735
b110000 !
b110000 (
1$
#1740
b1001 ,
0$
#1745
1$
#1750
b1001 #
b1001 &
0$
#1755
b110110 '
b1001 *
1$
#1760
0$
#1765
b110110 !
b110110 (
1$
#1770
b1010 ,
0$
#1775
1$
#1780
b1010 #
b1010 &
0$
#1785
b111100 '
b1010 *
1$
#1790
0$
#1795
b111100 !
b111100 (
1$
#1800
b111 +
b1 ,
0$
#1805
1$
#1810
b1 #
b1 &
b111 "
b111 %
0$
#1815
b1 *
b111 '
b111 )
1$
#1820
0$
#1825
b111 !
b111 (
1$
#1830
b10 ,
0$
#1835
1$
#1840
b10 #
b10 &
0$
#1845
b1110 '
b10 *
1$
#1850
0$
#1855
b1110 !
b1110 (
1$
#1860
b11 ,
0$
#1865
1$
#1870
b11 #
b11 &
0$
#1875
b10101 '
b11 *
1$
#1880
0$
#1885
b10101 !
b10101 (
1$
#1890
b100 ,
0$
#1895
1$
#1900
b100 #
b100 &
0$
#1905
b11100 '
b100 *
1$
#1910
0$
#1915
b11100 !
b11100 (
1$
#1920
b101 ,
0$
#1925
1$
#1930
b101 #
b101 &
0$
#1935
b100011 '
b101 *
1$
#1940
0$
#1945
b100011 !
b100011 (
1$
#1950
b110 ,
0$
#1955
1$
#1960
b110 #
b110 &
0$
#1965
b101010 '
b110 *
1$
#1970
0$
#1975
b101010 !
b101010 (
1$
#1980
b111 ,
0$
#1985
1$
#1990
b111 #
b111 &
0$
#1995
b110001 '
b111 *
1$
#2000
0$
#2005
b110001 !
b110001 (
1$
#2010
b1000 ,
0$
#2015
1$
#2020
b1000 #
b1000 &
0$
#2025
b111000 '
b1000 *
1$
#2030
0$
#2035
b111000 !
b111000 (
1$
#2040
b1001 ,
0$
#2045
1$
#2050
b1001 #
b1001 &
0$
#2055
b111111 '
b1001 *
1$
#2060
0$
#2065
b111111 !
b111111 (
1$
#2070
b1010 ,
0$
#2075
1$
#2080
b1010 #
b1010 &
0$
#2085
b1000110 '
b1010 *
1$
#2090
0$
#2095
b1000110 !
b1000110 (
1$
#2100
b1000 +
b1 ,
0$
#2105
1$
#2110
b1 #
b1 &
b1000 "
b1000 %
0$
#2115
b1 *
b1000 '
b1000 )
1$
#2120
0$
#2125
b1000 !
b1000 (
1$
#2130
b10 ,
0$
#2135
1$
#2140
b10 #
b10 &
0$
#2145
b10000 '
b10 *
1$
#2150
0$
#2155
b10000 !
b10000 (
1$
#2160
b11 ,
0$
#2165
1$
#2170
b11 #
b11 &
0$
#2175
b11000 '
b11 *
1$
#2180
0$
#2185
b11000 !
b11000 (
1$
#2190
b100 ,
0$
#2195
1$
#2200
b100 #
b100 &
0$
#2205
b100000 '
b100 *
1$
#2210
0$
#2215
b100000 !
b100000 (
1$
#2220
b101 ,
0$
#2225
1$
#2230
b101 #
b101 &
0$
#2235
b101000 '
b101 *
1$
#2240
0$
#2245
b101000 !
b101000 (
1$
#2250
b110 ,
0$
#2255
1$
#2260
b110 #
b110 &
0$
#2265
b110000 '
b110 *
1$
#2270
0$
#2275
b110000 !
b110000 (
1$
#2280
b111 ,
0$
#2285
1$
#2290
b111 #
b111 &
0$
#2295
b111000 '
b111 *
1$
#2300
0$
#2305
b111000 !
b111000 (
1$
#2310
b1000 ,
0$
#2315
1$
#2320
b1000 #
b1000 &
0$
#2325
b1000000 '
b1000 *
1$
#2330
0$
#2335
b1000000 !
b1000000 (
1$
#2340
b1001 ,
0$
#2345
1$
#2350
b1001 #
b1001 &
0$
#2355
b1001000 '
b1001 *
1$
#2360
0$
#2365
b1001000 !
b1001000 (
1$
#2370
b1010 ,
0$
#2375
1$
#2380
b1010 #
b1010 &
0$
#2385
b1010000 '
b1010 *
1$
#2390
0$
#2395
b1010000 !
b1010000 (
1$
#2400
b1001 +
b1 ,
0$
#2405
1$
#2410
b1 #
b1 &
b1001 "
b1001 %
0$
#2415
b1 *
b1001 '
b1001 )
1$
#2420
0$
#2425
b1001 !
b1001 (
1$
#2430
b10 ,
0$
#2435
1$
#2440
b10 #
b10 &
0$
#2445
b10010 '
b10 *
1$
#2450
0$
#2455
b10010 !
b10010 (
1$
#2460
b11 ,
0$
#2465
1$
#2470
b11 #
b11 &
0$
#2475
b11011 '
b11 *
1$
#2480
0$
#2485
b11011 !
b11011 (
1$
#2490
b100 ,
0$
#2495
1$
#2500
b100 #
b100 &
0$
#2505
b100100 '
b100 *
1$
#2510
0$
#2515
b100100 !
b100100 (
1$
#2520
b101 ,
0$
#2525
1$
#2530
b101 #
b101 &
0$
#2535
b101101 '
b101 *
1$
#2540
0$
#2545
b101101 !
b101101 (
1$
#2550
b110 ,
0$
#2555
1$
#2560
b110 #
b110 &
0$
#2565
b110110 '
b110 *
1$
#2570
0$
#2575
b110110 !
b110110 (
1$
#2580
b111 ,
0$
#2585
1$
#2590
b111 #
b111 &
0$
#2595
b111111 '
b111 *
1$
#2600
0$
#2605
b111111 !
b111111 (
1$
#2610
b1000 ,
0$
#2615
1$
#2620
b1000 #
b1000 &
0$
#2625
b1001000 '
b1000 *
1$
#2630
0$
#2635
b1001000 !
b1001000 (
1$
#2640
b1001 ,
0$
#2645
1$
#2650
b1001 #
b1001 &
0$
#2655
b1010001 '
b1001 *
1$
#2660
0$
#2665
b1010001 !
b1010001 (
1$
#2670
b1010 ,
0$
#2675
1$
#2680
b1010 #
b1010 &
0$
#2685
b1011010 '
b1010 *
1$
#2690
0$
#2695
b1011010 !
b1011010 (
1$
#2700
b1010 +
b1 ,
0$
#2705
1$
#2710
b1 #
b1 &
b1010 "
b1010 %
0$
#2715
b1 *
b1010 '
b1010 )
1$
#2720
0$
#2725
b1010 !
b1010 (
1$
#2730
b10 ,
0$
#2735
1$
#2740
b10 #
b10 &
0$
#2745
b10100 '
b10 *
1$
#2750
0$
#2755
b10100 !
b10100 (
1$
#2760
b11 ,
0$
#2765
1$
#2770
b11 #
b11 &
0$
#2775
b11110 '
b11 *
1$
#2780
0$
#2785
b11110 !
b11110 (
1$
#2790
b100 ,
0$
#2795
1$
#2800
b100 #
b100 &
0$
#2805
b101000 '
b100 *
1$
#2810
0$
#2815
b101000 !
b101000 (
1$
#2820
b101 ,
0$
#2825
1$
#2830
b101 #
b101 &
0$
#2835
b110010 '
b101 *
1$
#2840
0$
#2845
b110010 !
b110010 (
1$
#2850
b110 ,
0$
#2855
1$
#2860
b110 #
b110 &
0$
#2865
b111100 '
b110 *
1$
#2870
0$
#2875
b111100 !
b111100 (
1$
#2880
b111 ,
0$
#2885
1$
#2890
b111 #
b111 &
0$
#2895
b1000110 '
b111 *
1$
#2900
0$
#2905
b1000110 !
b1000110 (
1$
#2910
b1000 ,
0$
#2915
1$
#2920
b1000 #
b1000 &
0$
#2925
b1010000 '
b1000 *
1$
#2930
0$
#2935
b1010000 !
b1010000 (
1$
#2940
b1001 ,
0$
#2945
1$
#2950
b1001 #
b1001 &
0$
#2955
b1011010 '
b1001 *
1$
#2960
0$
#2965
b1011010 !
b1011010 (
1$
#2970
b1010 ,
0$
#2975
1$
#2980
b1010 #
b1010 &
0$
#2985
b1100100 '
b1010 *
1$
#2990
0$
#2995
b1100100 !
b1100100 (
1$
#3000
b1011 +
b1011 ,
0$
